PTT/__init__.py
PTT/adult.py
PTT/anime.py
PTT/cli.py
PTT/handlers.py
PTT/parse.py
PTT/transformers.py
PTT/keywords/combined-keywords.txt
PTT/keywords/short-adult-compound-words.txt
PTT/keywords/short-adult-words.txt
parsett-1.8.3.dist-info/METADATA
parsett-1.8.3.dist-info/WHEEL
parsett-1.8.3.dist-info/entry_points.txt
parsett-1.8.3.dist-info/licenses/LICENSE
parsett-1.8.3.dist-info/RECORD
