Metadata-Version: 2.4
Name: parsett
Version: 1.8.3
Summary: Parsett - Torrent Parser with Adult Content Detection
Author-email: Dreu LaVelle <dreu.lavelle@gmail.com>
License-Expression: MIT
License-File: LICENSE
Requires-Python: <4,>=3.10
Requires-Dist: arrow<2,>=1.3.0
Requires-Dist: regex<2026,>=2025.10.23
